tectonics/__init__.py
tectonics/revenue.py
tectonics/status_1.py
tectonics/_clique/__init__.py
tectonics/_clique/group/__init__.py
tectonics/_status/insurance.proc.py
tectonics/_status/insurance_clouds.proc.py
tectonics/autopilot/bt/strategies/example_1.py
tectonics/climate/__init__.py
tectonics/clouds/Alpaca/shares/retrieve.py
tectonics/clouds/Alpaca/shares/structure_1.py
tectonics/clouds/Alpaca/shares/_status/API_status_1.py
tectonics/clouds/CCXT/__init__.py
tectonics/clouds/CCXT/OHLCV/__init__.py
tectonics/clouds/CCXT/OHLCV/candles/__init__.py
tectonics/clouds/CCXT/OHLCV/candles_v1/__init__.py
tectonics/clouds/CCXT/symbols/array.py
tectonics/clouds/Coinbase/API/__init__.py
tectonics/clouds/Coinbase/API/build_JWT.py
tectonics/clouds/Coinbase/API/accounts/__init__.py
tectonics/clouds/Coinbase/API/orders/order_IDs.py
tectonics/clouds/Coinbase/API/products/candles.py
tectonics/clouds/Coinbase/API/products/catalogue.py
tectonics/clouds/Coinbase/orders/place.py
tectonics/clouds/Tradier/_status/API_status_combine_1.py
tectonics/clouds/Tradier/procedures/options/combine.py
tectonics/clouds/Tradier/v1/markets/options/chains/__init__.py
tectonics/clouds/Tradier/v1/markets/options/chains/parse_1.py
tectonics/clouds/Tradier/v1/markets/options/expirations/__init__.py
tectonics/clouds/TradingView/sensors/__init__.py
tectonics/clouds/Yahoo/retrieve.py
tectonics/gadgets/format_percentage.py
tectonics/gadgets/ratio.py
tectonics/gadgets/clock/UTC/ISO.py
tectonics/gadgets/clock/UTC/greatness_1.py
tectonics/gadgets/math/slope/__init__.py
tectonics/gadgets/pandas/DF/from_list.py
tectonics/gadgets/pandas/DF/to_list.py
tectonics/gadgets/pandas/DF/_status/status_from_1.py
tectonics/gadgets/summation/__init__.py
tectonics/gadgets/summation/status_1.py
tectonics/groups/USA/forms/SEC/6K/__init__.py
tectonics/groups/USA/forms/balance_sheets/__init__.py
tectonics/groups/USA/forms/balance_sheets/equity/__init__.py
tectonics/groups/USA/forms/income/__init__.py
tectonics-1.0.2.dist-info/METADATA
tectonics-1.0.2.dist-info/WHEEL
tectonics-1.0.2.dist-info/entry_points.txt
tectonics-1.0.2.dist-info/top_level.txt
tectonics-1.0.2.dist-info/RECORD
